score.sa.db-0.2.1-py3.7-nspkg.pth
score/sa/db/__init__.py
score/sa/db/_enum.py
score/sa/db/_init.py
score/sa/db/pg.py
score/sa/db/sqlite.py
score.sa.db-0.2.1.dist-info/COPYING.LESSER.txt
score.sa.db-0.2.1.dist-info/METADATA
score.sa.db-0.2.1.dist-info/WHEEL
score.sa.db-0.2.1.dist-info/namespace_packages.txt
score.sa.db-0.2.1.dist-info/top_level.txt
score.sa.db-0.2.1.dist-info/RECORD
