Metadata-Version: 2.1
Name: score.sa.db
Version: 0.2.1
Summary: Database connectivity for The SCORE Framework
Home-page: http://score-framework.org
Author: strg.at
Author-email: score@strg.at
License: LGPL
Keywords: score framework database sqlalchemy
Classifier: Development Status :: 4 - Beta
Classifier: Environment :: Console
Classifier: Environment :: Web Environment
Classifier: Intended Audience :: Developers
Classifier: License :: OSI Approved :: GNU Lesser General Public License v3 or later (LGPLv3+)
Classifier: Operating System :: OS Independent
Classifier: Programming Language :: SQL
Classifier: Programming Language :: Python :: 3
Classifier: Programming Language :: Python :: 3.4
Classifier: Topic :: Software Development :: Libraries :: Application Frameworks
Classifier: Topic :: Database :: Front-Ends
License-File: COPYING.LESSER.txt
Requires-Dist: score.init (>=0.3)
Requires-Dist: SQLAlchemy (>=0.9)
Requires-Dist: zope.sqlalchemy (<1.4,>=0.7)
